[
{
  "login": "Birthdays",
  "id": 423638,
  "node_id": "MDEyOk9yZ2FuaXphdGlvbjQyMzYzOA==",
  "avatar_url": "https://smartcity.curs.kz/SmartArsu/Resources/History/Birthdays.png",
},
{
  "login": "Birthdays",
  "id": 423638,
  "node_id": "MDEyOk9yZ2FuaXphdGlvbjQyMzYzOA==",
  "avatar_url": "https://smartcity.curs.kz/SmartArsu/Resources/History/Birthdays.png",
},
{
  "login": "News",
  "id": 423638,
  "node_id": "MDEyOk9yZ2FuaXphdGlvbjQyMzYzOA==",
  "avatar_url": "https://smartcity.curs.kz/SmartArsu/Resources/History/News.png",
},
{
  "login": «Ads,
  "id": 423638,
  "node_id": "MDEyOk9yZ2FuaXphdGlvbjQyMzYzOA==",
  "avatar_url": "https://smartcity.curs.kz/SmartArsu/Resources/History/Ads.png",
},
{
  "login": "Voting",
  "id": 423638,
  "node_id": "MDEyOk9yZ2FuaXphdGlvbjQyMzYzOA==",
  "avatar_url": "https://smartcity.curs.kz/SmartArsu/Resources/History/Voting.png",
}
]
